ezQgd.py
simplify.py
qasm_to_qcis/__init__.py
qasm_to_qcis/const.py
qasm_to_qcis/qasm.py
qasm_to_qcis/qasm_to_qcis.py
qcis_to_qasm/__init__.py
qcis_to_qasm/const.py
qcis_to_qasm/qcis.py
qcis_to_qasm/qcis_to_qasm.py
ezQgd-1.0.10.dist-info/METADATA
ezQgd-1.0.10.dist-info/WHEEL
ezQgd-1.0.10.dist-info/top_level.txt
ezQgd-1.0.10.dist-info/RECORD
