Metadata-Version: 2.1
Name: ezQgd
Version: 1.0.10
Summary: A SDK to use Quantum Computer @ quantumctek-cloud.com with QCIS.
Home-page: https://quantumctek-cloud.com
Author: Code42
Author-email: support@quantumctek-cloud.com
License: MIT
Classifier: License :: OSI Approved :: MIT License
Classifier: Programming Language :: Python
Classifier: Programming Language :: Python :: 3
Classifier: Programming Language :: Python :: 3.6
Classifier: Programming Language :: Python :: Implementation :: CPython
Classifier: Programming Language :: Python :: Implementation :: PyPy
Requires-Python: >=3.6.0
Requires-Dist: beautifulsoup4
Requires-Dist: numpy
Requires-Dist: requests
Requires-Dist: isqmap
Requires-Dist: sabreMapper
